{
  "backup_meta": {
    "backed_up_at": "2026-02-18T06:26:04.043101Z",
    "operation": "delete",
    "original_path": "C:\\Users\\sibag\\.agent\\memory\\episodes\\ep_20260217_063744_4lo91k.json",
    "original_hash": "80022e15e0fb4f79"
  },
  "artifact": {
    "id": "ep_20260217_063744_4lo91k",
    "type": "episode",
    "version": "1.0",
    "created_at": "2026-02-17T06:37:44.236430Z",
    "updated_at": "2026-02-17T06:37:44.362385Z",
    "sensitivity": "internal",
    "tags": [
      "smoke-test",
      "auto-update"
    ],
    "source": {
      "workflow": "manual",
      "run_id": null,
      "tool_trace_path": null
    },
    "data": {
      "goal": "Smoke test - skill auto-update",
      "status": "closed",
      "plan": [
        "Test auto skill updates"
      ],
      "context": {
        "test_type": "auto_skill_update"
      },
      "actions": [],
      "result": "success",
      "result_summary": "Auto skill update test",
      "links": {
        "facts_created": [],
        "decisions_created": [],
        "decisions_used": [],
        "skills_used": [
          "auto_test"
        ],
        "evaluation_id": "eval_20260217_063744_bxqshf"
      },
      "started_at": "2026-02-17T06:37:44.236430Z",
      "closed_at": "2026-02-17T06:37:44.289199Z",
      "duration_mins": 0.0,
      "warnings": []
    }
  }
}