{
  "id": "log_20260216_142900_yhxp83",
  "type": "log",
  "version": "1.0",
  "created_at": "2026-02-15T09:06:00Z",
  "updated_at": null,
  "sensitivity": "internal",
  "tags": [
    "migrated",
    "archive-recovery",
    "timestamp-corrected"
  ],
  "source": {
    "workflow": "migration",
    "run_id": null,
    "tool_trace_path": null
  },
  "data": {
    "event_type": "task_complete",
    "message": "Proved DURO OS effectiveness with Lore V1 vs V2 comparison: V1 (instinct-driven): 25/30 (83%). V2 (OS-driven): 30/30 (100%). Key fixes: mood sentence first, CTA at flow end, strict Mondrian grid before breaks, named discord, declared rhythm motif. Proves process catches problems before they compound.",
    "task": "Proved DURO OS effectiveness with Lore V1 vs V2 comparison",
    "outcome": "V1 (instinct-driven): 25/30 (83%). V2 (OS-driven): 30/30 (100%). Key fixes: mood sentence first, CTA at flow end, strict Mondrian grid before breaks, named discord, declared rhythm motif. Proves process catches problems before they compound.",
    "error": null,
    "lesson": null,
    "duration_ms": null
  }
}