{
  "id": "log_20260216_142904_goj7er",
  "type": "log",
  "version": "1.0",
  "created_at": "2026-02-13T08:34:00Z",
  "updated_at": null,
  "sensitivity": "internal",
  "tags": [
    "migrated",
    "archive-recovery",
    "Design",
    "timestamp-corrected"
  ],
  "source": {
    "workflow": "migration",
    "run_id": null,
    "tool_trace_path": null
  },
  "data": {
    "event_type": "learning",
    "message": "3D effects require consistent light physics: if shadows fall bottom-right, then light source is top-left, highlights must be on top/left edges, and reflections in top-left area. Inconsistencies are detected subconsciously even when not articulated.",
    "task": null,
    "outcome": null,
    "error": null,
    "lesson": null,
    "duration_ms": null
  }
}