{
  "id": "log_20260216_142906_lkf1me",
  "type": "log",
  "version": "1.0",
  "created_at": "2026-02-14T10:34:00Z",
  "updated_at": null,
  "sensitivity": "internal",
  "tags": [
    "migrated",
    "archive-recovery",
    "Process",
    "timestamp-corrected"
  ],
  "source": {
    "workflow": "migration",
    "run_id": null,
    "tool_trace_path": null
  },
  "data": {
    "event_type": "learning",
    "message": "Established V6 Cinematch design workflow: 1) Design in Pencil with mockup approval, 2) Run Design Study Pack critique checklist (6 dimensions, target 24+/30), 3) Identify gaps like missing state coverage, 4) Design states (loading/empty/error) in Pencil, 5) Get approval, 6) Implement in code. This ensures quality gates before coding.",
    "task": null,
    "outcome": null,
    "error": null,
    "lesson": null,
    "duration_ms": null
  }
}