{
  "id": "log_20260219_062908_3e1t5g",
  "type": "log",
  "version": "1.0",
  "created_at": "2026-02-19T06:29:08.288337Z",
  "updated_at": null,
  "sensitivity": "internal",
  "tags": [],
  "source": {
    "workflow": "session",
    "run_id": null,
    "tool_trace_path": null
  },
  "data": {
    "event_type": "task_complete",
    "message": "Implement workspace guard (Layer 2 security): Created workspace_guard.py with: path scoping to DURO_WORKSPACE, path traversal detection (.., symlinks, unicode confusables), high-risk path patterns requiring approval (.env, credentials, .ssh), bash command path extraction. Integrated into policy gate - workspace check runs after autonomy approval. Default workspace is ~/.agent. Added tools: duro_workspace_status, duro_workspace_add, duro_workspace_validate. All tests passing, pushed to security/policy-gate-exec-path branch.",
    "task": "Implement workspace guard (Layer 2 security)",
    "outcome": "Created workspace_guard.py with: path scoping to DURO_WORKSPACE, path traversal detection (.., symlinks, unicode confusables), high-risk path patterns requiring approval (.env, credentials, .ssh), bash command path extraction. Integrated into policy gate - workspace check runs after autonomy approval. Default workspace is ~/.agent. Added tools: duro_workspace_status, duro_workspace_add, duro_workspace_validate. All tests passing, pushed to security/policy-gate-exec-path branch.",
    "error": null,
    "lesson": null,
    "duration_ms": null
  }
}