{
  "id": "log_20260216_142903_0wrd6x",
  "type": "log",
  "version": "1.0",
  "created_at": "2026-02-12T11:01:00Z",
  "updated_at": null,
  "sensitivity": "internal",
  "tags": [
    "migrated",
    "archive-recovery",
    "Process",
    "timestamp-corrected"
  ],
  "source": {
    "workflow": "migration",
    "run_id": null,
    "tool_trace_path": null
  },
  "data": {
    "event_type": "learning",
    "message": "When implementing designs from pencil.dev mock-ups for Intersphere: 1) Always systematically list ALL mock-ups first and cross-reference with ALL pages in codebase. 2) Don't just update colors - match the actual layout structure, spacing, and component hierarchy. 3) Verify each page visually after deployment. User confirmed Homepage and Explore look great, but Search, Discover, Quiz, and Topic Detail pages need more layout work beyond just dark theme colors.",
    "task": null,
    "outcome": null,
    "error": null,
    "lesson": null,
    "duration_ms": null
  }
}