{
  "id": "log_20260216_141700_wg6f7f",
  "type": "log",
  "version": "1.0",
  "created_at": "2026-02-16T14:17:00.570447Z",
  "updated_at": null,
  "sensitivity": "internal",
  "tags": [],
  "source": {
    "workflow": "session",
    "run_id": null,
    "tool_trace_path": null
  },
  "data": {
    "event_type": "task_complete",
    "message": "Add logging safeguards to prevent silent failures: Added return value checking to all 4 logging handlers + warning logs on failure + TEST 8 in smoke suite to catch regressions. Commit bf211ea pushed.",
    "task": "Add logging safeguards to prevent silent failures",
    "outcome": "Added return value checking to all 4 logging handlers + warning logs on failure + TEST 8 in smoke suite to catch regressions. Commit bf211ea pushed.",
    "error": null,
    "lesson": null,
    "duration_ms": null
  }
}