{
  "id": "fact_20260214_050733_8s2exy",
  "type": "fact",
  "version": "1.1",
  "created_at": "2026-02-14T05:07:33.743130Z",
  "updated_at": null,
  "sensitivity": "public",
  "tags": [
    "cinematch",
    "component-library",
    "pencil",
    "design"
  ],
  "source": {
    "workflow": "manual",
    "run_id": null,
    "tool_trace_path": null
  },
  "data": {
    "claim": "Cinematch component library created in Pencil with 10 reusable components: Button/Primary, Button/Secondary, Button/Outline, Button/Ghost, Input/Default, Input/WithIcon, Card/Default, Badge/Default, Badge/Primary, Badge/Outline, Badge/Success, Avatar/Large, Avatar/Medium, Avatar/Small, Avatar/WithStatus",
    "source_urls": [],
    "snippet": null,
    "confidence": 0.5,
    "verified": false,
    "evidence_type": "quote",
    "provenance": "tool_output"
  }
}